MANIFEST.in
README.md
setup.py
hcache/LICENSE
hcache/README.md
hcache/__init__.py
hcache/cache.py
hcache/storages/FileStorage.py
hcache/storages/LocalStorage.py
hcache/storages/MemcachedStorage.py
hcache/storages/RedisStorage.py
hcache/storages/__init__.py
hcache/utils/CacheUtil.py
hcache/utils/__init__.py
hehey_hcache.egg-info/PKG-INFO
hehey_hcache.egg-info/SOURCES.txt
hehey_hcache.egg-info/dependency_links.txt
hehey_hcache.egg-info/top_level.txt