Metadata-Version: 2.1
Name: hehey-hcache
Version: 1.0.1
Summary: hehey-hcache 是一个python 数据缓存工具组件
Home-page: https://gitee.com/chinahehe/hehey-hcache
Author: 13564768842
Author-email: chinabluexfw@163.com
License: UNKNOWN
Platform: UNKNOWN
